grandma_stock_valuation/__init__.py
grandma_stock_valuation/load_package_data.py
grandma_stock_valuation/portfolio_allocator.py
grandma_stock_valuation/valuation_model.py
grandma_stock_valuation/yahoo_data_loader.py
grandma_stock_valuation/data/EEMA_EOD.csv.gz
grandma_stock_valuation/data/IEV_EOD.csv.gz
grandma_stock_valuation/data/IVV_EOD.csv.gz
grandma_stock_valuation/data/VPL_EOD.csv.gz
grandma_stock_valuation/utils/__init__.py
grandma_stock_valuation/utils/logger.py
grandma_stock_valuation-0.2.2.dist-info/LICENSE.txt
grandma_stock_valuation-0.2.2.dist-info/METADATA
grandma_stock_valuation-0.2.2.dist-info/WHEEL
grandma_stock_valuation-0.2.2.dist-info/top_level.txt
grandma_stock_valuation-0.2.2.dist-info/RECORD
